betterletter/__init__.py
betterletter/__main__.py
betterletter/io.py
betterletter/iteration.py
betterletter/resources/dicts/README.md
betterletter/resources/dicts/de.txt
betterletter/resources/languages.json
betterletter/strings.py
betterletter/substituters.py
betterletter-1.2.1.dist-info/LICENSE
betterletter-1.2.1.dist-info/METADATA
betterletter-1.2.1.dist-info/WHEEL
betterletter-1.2.1.dist-info/entry_points.txt
betterletter-1.2.1.dist-info/RECORD
