Metadata-Version: 2.1
Name: betterletter
Version: 1.2.1
Summary: Substitute alternative spellings of native characters (e.g. German umlauts [ae, oe, ue] etc. [ss]) with their correct versions (ä, ö, ü, ß).
Home-page: https://github.com/alexpovel/betterletter/
License: MIT
Keywords: spelling,umlaut,substitute,letter,alternative
Author: Alex Povel
Author-email: python@alexpovel.de
Requires-Python: >=3.9,<4.0
Classifier: Intended Audience :: End Users/Desktop
Classifier: License :: OSI Approved :: MIT License
Classifier: Natural Language :: English
Classifier: Natural Language :: German
Classifier: Operating System :: OS Independent
Classifier: Programming Language :: Python :: 3
Classifier: Programming Language :: Python :: 3.9
Classifier: Programming Language :: Python :: 3.10
Classifier: Programming Language :: Python :: 3.11
Classifier: Topic :: Communications
Classifier: Topic :: Office/Business
Classifier: Topic :: Text Editors
Classifier: Topic :: Text Processing
Classifier: Topic :: Utilities
Classifier: Typing :: Typed
Requires-Dist: pyperclip (>=1.8.2,<2.0.0)
Project-URL: Bug Tracker, https://github.com/alexpovel/betterletter/issues
Project-URL: Repository, https://github.com/alexpovel/betterletter/
